aisen/__init__.py
aisen/client.py
aisen/exceptions.py
aisen-0.1.0.dist-info/licenses/LICENSE
aisen-0.1.0.dist-info/METADATA
aisen-0.1.0.dist-info/WHEEL
aisen-0.1.0.dist-info/top_level.txt
aisen-0.1.0.dist-info/RECORD
