Metadata-Version: 2.4
Name: aisen
Version: 0.1.0
Summary: Python SDK for aisen.vn API
Author-email: LLaSea <llasea@gmail.com>
License: MIT License
Project-URL: Homepage, https://aisen.vn
Project-URL: Documentation, https://docs.aisen.vn
Project-URL: Repository, https://github.com/aisen-vn/aisen-python-sdk
Project-URL: Bug Tracker, https://github.com/aisen-vn/aisen-python-sdk/issues
Keywords: aisen,ai,api,sdk,vietnam
Classifier: Development Status :: 3 - Alpha
Classifier: Intended Audience :: Developers
Classifier: License :: OSI Approved :: MIT License
Classifier: Programming Language :: Python :: 3
Classifier: Programming Language :: Python :: 3.8
Classifier: Programming Language :: Python :: 3.9
Classifier: Programming Language :: Python :: 3.10
Classifier: Programming Language :: Python :: 3.11
Classifier: Programming Language :: Python :: 3.12
Classifier: Programming Language :: Python :: 3.13
Classifier: Programming Language :: Python :: 3.14
Requires-Python: >=3.8
License-File: LICENSE
Requires-Dist: requests>=2.25.0
Requires-Dist: typing-extensions>=4.0.0
Provides-Extra: dev
Requires-Dist: pytest>=6.0; extra == "dev"
Requires-Dist: pytest-cov; extra == "dev"
Requires-Dist: black; extra == "dev"
Requires-Dist: flake8; extra == "dev"
Requires-Dist: mypy; extra == "dev"
Dynamic: license-file
